neurom/__init__.py
neurom/exceptions.py
neurom/morphmath.py
neurom/stats.py
neurom/utils.py
neurom/apps/__init__.py
neurom/apps/annotate.py
neurom/apps/cli.py
neurom/apps/morph_check.py
neurom/apps/morph_stats.py
neurom/apps/config/morph_check.yaml
neurom/apps/config/morph_stats.yaml
neurom/check/__init__.py
neurom/check/morphology_checks.py
neurom/check/morphtree.py
neurom/check/runner.py
neurom/core/__init__.py
neurom/core/dataformat.py
neurom/core/morphology.py
neurom/core/population.py
neurom/core/soma.py
neurom/core/types.py
neurom/features/__init__.py
neurom/features/bifurcation.py
neurom/features/morphology.py
neurom/features/neurite.py
neurom/features/population.py
neurom/features/section.py
neurom/geom/__init__.py
neurom/geom/transform.py
neurom/io/__init__.py
neurom/io/utils.py
neurom/view/__init__.py
neurom/view/dendrogram.py
neurom/view/matplotlib_impl.py
neurom/view/matplotlib_utils.py
neurom/view/plotly_impl.py
neurom-4.0.4.dist-info/AUTHORS.md
neurom-4.0.4.dist-info/LICENSE.txt
neurom-4.0.4.dist-info/METADATA
neurom-4.0.4.dist-info/WHEEL
neurom-4.0.4.dist-info/entry_points.txt
neurom-4.0.4.dist-info/top_level.txt
neurom-4.0.4.dist-info/RECORD
