Metadata-Version: 2.1
Name: neurom
Version: 4.0.4
Summary: NeuroM: a light-weight neuron morphology analysis package
Author: Blue Brain Project, EPFL
License: Copyright (c) 2015-2022 Blue Brain Project/EPFL 
Project-URL: Homepage, https://github.com/BlueBrain/NeuroM
Project-URL: Repository, https://github.com/BlueBrain/NeuroM.git
Project-URL: Documentation, https://neurom.readthedocs.io/
Project-URL: Tracker, https://github.com/BlueBrain/NeuroM/issues
Classifier: Development Status :: 6 - Mature
Classifier: Intended Audience :: Education
Classifier: Intended Audience :: Science/Research
Classifier: Programming Language :: Python
Classifier: Programming Language :: Python :: 3.9
Classifier: Programming Language :: Python :: 3.10
Classifier: Programming Language :: Python :: 3.11
Classifier: Programming Language :: Python :: 3.12
Classifier: Programming Language :: Python :: 3.13
Classifier: Topic :: Scientific/Engineering :: Bio-Informatics
Requires-Python: >=3.9
License-File: LICENSE.txt
License-File: AUTHORS.md
Requires-Dist: click>=7.0
Requires-Dist: matplotlib>=3.2.1
Requires-Dist: morphio>=3.3.6
Requires-Dist: numpy>=1.8.0
Requires-Dist: pandas>=1.0.5
Requires-Dist: pyyaml>=3.10
Requires-Dist: scipy>=1.2.0
Requires-Dist: tqdm>=4.8.4
Requires-Dist: cached_property>=1.5.1
Requires-Dist: importlib_resources>=1.3; python_version < "3.9"
Provides-Extra: plotly
Requires-Dist: plotly>=3.6.0; extra == "plotly"
Requires-Dist: psutil>=5.5.1; extra == "plotly"
Provides-Extra: docs
Requires-Dist: sphinx-bluebrain-theme; extra == "docs"
Requires-Dist: sphinx-autorun; extra == "docs"
